{"cameraMode":{"drawMode":0,"name":"Shaded","section":"Shading Mode"},"sceneLighting":false,"audioPlay":false,"sceneViewState":{"m_AlwaysRefresh":false,"showFog":true,"showSkybox":false,"showFlares":true,"showImageEffects":true,"showParticleSystems":true,"showVisualEffectGraphs":true,"m_FxEnabled":true},"in2DMode":false,"pivot":{"x":0.0,"y":0.23187249898910523,"z":-0.0000050067901611328128},"rotation":{"x":0.26508280634880068,"y":0.39610299468040469,"z":-0.12057892978191376,"w":0.8708012700080872},"size":1.0265575647354127,"orthographic":true}